lezgi_numbers/__init__.py
lezgi_numbers/constants.py
lezgi_numbers/lezgiToNum.py
lezgi_numbers/numToLezgi.py
tests/__init__.py
tests/test_lezgiToNum.py
tests/test_numToLezgi.py
lezgi_numbers-0.1.1.dist-info/LICENSE
lezgi_numbers-0.1.1.dist-info/METADATA
lezgi_numbers-0.1.1.dist-info/WHEEL
lezgi_numbers-0.1.1.dist-info/top_level.txt
lezgi_numbers-0.1.1.dist-info/RECORD
