Metadata-Version: 2.1
Name: lezgi-numbers
Version: 0.1.1
Summary: A Python package for converting numbers to Lezgi numerals and back.
Home-page: https://github.com/LekiTech/lezgi-numbers-python
Author: Kamran Tadzjibov
Keywords: lezgi numbers conversion localization
Classifier: Programming Language :: Python :: 3
Classifier: Intended Audience :: Developers
Classifier: Topic :: Software Development :: Localization
Classifier: License :: OSI Approved :: MIT License
Classifier: Operating System :: OS Independent
Requires-Python: >=3.6
License-File: LICENSE
